kerbad/__init__.py
kerbad/_version.py
kerbad/aioclient.py
kerbad/client.py
kerbad/pkinit.py
kerbad/security.py
kerbad/tickettest.py
kerbad/common/__init__.py
kerbad/common/ccache.py
kerbad/common/constants.py
kerbad/common/creds.py
kerbad/common/factory.py
kerbad/common/keytab.py
kerbad/common/kirbi.py
kerbad/common/spn.py
kerbad/common/target.py
kerbad/common/utils.py
kerbad/common/windows/__init__.py
kerbad/common/windows/crypt32.py
kerbad/common/windows/defines.py
kerbad/examples/CVE_2022_33647.py
kerbad/examples/CVE_2022_33679.py
kerbad/examples/__init__.py
kerbad/examples/__main__.py
kerbad/examples/asreproast.py
kerbad/examples/ccache2kirbi.py
kerbad/examples/ccache_editor.py
kerbad/examples/ccacheroast.py
kerbad/examples/changepassword.py
kerbad/examples/crosstest.py
kerbad/examples/getNT.py
kerbad/examples/getS4U2proxy.py
kerbad/examples/getS4U2self.py
kerbad/examples/getTGS.py
kerbad/examples/getTGT.py
kerbad/examples/kerb23hashdecrypt.py
kerbad/examples/keylist.py
kerbad/examples/kirbi2ccache.py
kerbad/examples/spnroast.py
kerbad/gssapi/__init__.py
kerbad/gssapi/channelbindings.py
kerbad/gssapi/gssapi.py
kerbad/network/__init__.py
kerbad/network/aioclientsocket.py
kerbad/network/clientsocket.py
kerbad/protocol/__init__.py
kerbad/protocol/asn1_structs.py
kerbad/protocol/constants.py
kerbad/protocol/dirtydh.py
kerbad/protocol/encryption.py
kerbad/protocol/errors.py
kerbad/protocol/mskile.py
kerbad/protocol/rfc3244.py
kerbad/protocol/rfc4556.py
kerbad/protocol/rfc_iakerb.py
kerbad/protocol/structures.py
kerbad/protocol/ticketutils.py
kerbad/protocol/external/__init__.py
kerbad/protocol/external/dtypes.py
kerbad/protocol/external/enum.py
kerbad/protocol/external/ndr.py
kerbad/protocol/external/nrpc.py
kerbad/protocol/external/pac.py
kerbad/protocol/external/rpcrt.py
kerbad/protocol/external/structure.py
kerbad/protocol/external/ticketutil.py
kerbad-0.5.9.dist-info/licenses/LICENSE
kerbad-0.5.9.dist-info/METADATA
kerbad-0.5.9.dist-info/WHEEL
kerbad-0.5.9.dist-info/entry_points.txt
kerbad-0.5.9.dist-info/top_level.txt
kerbad-0.5.9.dist-info/zip-safe
kerbad-0.5.9.dist-info/RECORD
